{"match_id": "03e6d33d-39cd-4c0c-a936-177fd09d87c7", "map_id": "AmbroseValley", "date": "February_10", "duration_s": 454, "human_count": 1, "bot_count": 11, "bot_kills_inferred": 11, "bot_deaths_inferred": 1, "players": [{"user_id": "677aa632-3c51-4b64-a8d5-4762c78609f1", "is_bot": false, "positions": [[298.65, 897.63, 0], [323.25, 873.79, 20], [352.61, 877.08, 25], [355.28, 882.75, 30], [359.71, 889.2, 35], [360.96, 892.26, 40], [364.0, 885.38, 61], [363.98, 881.01, 66], [371.07, 896.1, 71], [381.87, 894.98, 76], [381.71, 882.7, 81], [394.67, 853.49, 86], [399.13, 847.22, 91], [401.96, 823.95, 101], [406.22, 820.34, 106], [420.04, 800.83, 111], [407.82, 797.8, 131], [409.43, 805.52, 136], [416.15, 799.26, 141], [419.18, 790.72, 146], [427.57, 789.94, 151], [439.84, 797.72, 156], [458.1, 808.78, 161], [465.71, 804.17, 166], [468.39, 804.24, 171], [470.52, 807.88, 176], [483.97, 811.69, 186], [508.15, 809.09, 191], [517.36, 794.03, 196], [530.05, 794.82, 201], [527.67, 798.77, 211], [518.52, 801.41, 217], [516.16, 812.12, 222], [507.35, 822.07, 227], [518.97, 806.88, 232], [527.31, 797.46, 237], [542.24, 794.03, 242], [545.14, 779.99, 247], [546.82, 790.81, 257], [544.84, 807.65, 262], [532.95, 786.19, 277], [527.97, 783.09, 282], [530.48, 784.71, 287], [532.38, 795.72, 292], [533.63, 781.15, 297], [542.82, 778.62, 302], [553.69, 802.81, 307], [549.4, 802.06, 312], [527.13, 773.74, 317], [507.29, 754.72, 322], [482.89, 728.23, 327], [463.87, 701.9, 332], [442.76, 684.3, 337], [423.45, 661.39, 342], [416.23, 649.17, 347], [413.53, 638.18, 352], [420.01, 630.53, 357], [409.39, 599.01, 362], [387.36, 574.68, 367], [383.91, 570.27, 372], [385.83, 547.55, 377], [390.34, 525.66, 382], [394.44, 515.38, 392], [398.17, 506.95, 398], [399.41, 494.3, 403], [406.55, 484.76, 408], [411.06, 485.19, 413], [424.49, 491.76, 418], [430.54, 494.8, 423], [435.35, 495.31, 428], [441.34, 493.66, 433], [450.25, 496.33, 438], [457.62, 501.06, 443], [469.51, 503.4, 448], [473.67, 508.65, 453]], "events": [{"type": "loot", "px": 354.66, "py": 881.9, "t": 29, "raw": "Loot"}, {"type": "loot", "px": 359.01, "py": 889.37, "t": 36, "raw": "Loot"}, {"type": "loot", "px": 360.62, "py": 892.43, "t": 43, "raw": "Loot"}, {"type": "loot", "px": 360.83, "py": 893.68, "t": 45, "raw": "Loot"}, {"type": "loot", "px": 360.68, "py": 891.41, "t": 51, "raw": "Loot"}, {"type": "loot", "px": 363.98, "py": 881.01, "t": 65, "raw": "Loot"}, {"type": "loot", "px": 363.98, "py": 881.01, "t": 65, "raw": "Loot"}, {"type": "loot", "px": 381.87, "py": 894.98, "t": 78, "raw": "Loot"}, {"type": "loot", "px": 402.05, "py": 823.98, "t": 103, "raw": "Loot"}, {"type": "loot", "px": 420.04, "py": 800.83, "t": 111, "raw": "Loot"}, {"type": "loot", "px": 420.46, "py": 801.12, "t": 123, "raw": "Loot"}, {"type": "loot", "px": 407.82, "py": 797.8, "t": 132, "raw": "Loot"}, {"type": "kill", "px": 471.01, "py": 804.62, "t": 168, "raw": "BotKill"}, {"type": "loot", "px": 480.82, "py": 811.52, "t": 184, "raw": "Loot"}, {"type": "loot", "px": 480.82, "py": 811.52, "t": 184, "raw": "Loot"}, {"type": "loot", "px": 530.05, "py": 794.82, "t": 203, "raw": "Loot"}, {"type": "kill", "px": 517.33, "py": 809.92, "t": 220, "raw": "BotKill"}, {"type": "loot", "px": 507.35, "py": 822.07, "t": 226, "raw": "Loot"}, {"type": "loot", "px": 507.35, "py": 822.07, "t": 226, "raw": "Loot"}, {"type": "loot", "px": 542.62, "py": 777.81, "t": 251, "raw": "Loot"}, {"type": "kill", "px": 529.87, "py": 783.49, "t": 286, "raw": "BotKill"}, {"type": "loot", "px": 528.37, "py": 788.74, "t": 289, "raw": "Loot"}, {"type": "loot", "px": 528.37, "py": 788.74, "t": 289, "raw": "Loot"}, {"type": "loot", "px": 537.25, "py": 775.07, "t": 299, "raw": "Loot"}, {"type": "loot", "px": 556.06, "py": 810.58, "t": 309, "raw": "Loot"}, {"type": "kill", "px": 418.59, "py": 657.3, "t": 344, "raw": "BotKill"}, {"type": "kill", "px": 414.98, "py": 642.91, "t": 350, "raw": "BotKill"}, {"type": "loot", "px": 413.53, "py": 638.18, "t": 352, "raw": "Loot"}, {"type": "loot", "px": 413.53, "py": 638.18, "t": 352, "raw": "Loot"}, {"type": "loot", "px": 417.61, "py": 637.02, "t": 354, "raw": "Loot"}, {"type": "loot", "px": 417.61, "py": 637.02, "t": 354, "raw": "Loot"}, {"type": "kill", "px": 383.66, "py": 571.86, "t": 371, "raw": "BotKill"}, {"type": "loot", "px": 384.96, "py": 561.57, "t": 375, "raw": "Loot"}, {"type": "loot", "px": 384.96, "py": 561.57, "t": 375, "raw": "Loot"}, {"type": "kill", "px": 396.3, "py": 506.8, "t": 396, "raw": "BotKill"}, {"type": "loot", "px": 404.61, "py": 484.37, "t": 406, "raw": "Loot"}, {"type": "loot", "px": 404.61, "py": 484.37, "t": 406, "raw": "Loot"}, {"type": "loot", "px": 427.73, "py": 493.21, "t": 419, "raw": "Loot"}, {"type": "kill", "px": 441.34, "py": 493.66, "t": 432, "raw": "BotKill"}, {"type": "kill", "px": 447.28, "py": 494.27, "t": 436, "raw": "BotKill"}, {"type": "kill", "px": 454.25, "py": 495.88, "t": 440, "raw": "BotKill"}, {"type": "kill", "px": 469.51, "py": 503.4, "t": 447, "raw": "BotKill"}, {"type": "death", "px": 474.34, "py": 509.72, "t": 454, "raw": "BotKilled"}], "raw_events": ["Position", "Position", "Position", "Loot", "Position", "Position", "Loot", "Position", "Loot", "Loot", "Loot", "Position", "Loot", "Loot", "Position", "Position", "Position", "Loot", "Position", "Position", "Position", "Position", "Loot", "Position", "Position", "Loot", "Loot", "Position", "Loot", "Position", "Position", "Position", "Position", "Position", "Position", "Position", "BotKill", "Position", "Position", "Loot", "Loot", "Position", "Position", "Position", "Position", "Loot", "Position", "Position", "BotKill", "Position", "Loot", "Loot", "Position", "Position", "Position", "Position", "Position", "Loot", "Position", "Position", "Position", "Position", "BotKill", "Position", "Loot", "Loot", "Position", "Position", "Loot", "Position", "Position", "Loot", "Position", "Position", "Position", "Position", "Position", "Position", "Position", "BotKill", "Position", "BotKill", "Position", "Loot", "Loot", "Loot", "Loot", "Position", "Position", "Position", "BotKill", "Position", "Loot", "Loot", "Position", "Position", "Position", "BotKill", "Position", "Position", "Loot", "Loot", "Position", "Position", "Position", "Loot", "Position", "Position", "BotKill", "Position", "BotKill", "Position", "BotKill", "Position", "BotKill", "Position", "Position", "BotKilled"]}, {"user_id": "inferred_bot_1", "is_bot": true, "positions": [], "events": [{"type": "death", "px": 471.01, "py": 804.62, "t": 168, "raw": "BotKilled"}]}, {"user_id": "inferred_bot_2", "is_bot": true, "positions": [], "events": [{"type": "death", "px": 517.33, "py": 809.92, "t": 220, "raw": "BotKilled"}]}, {"user_id": "inferred_bot_3", "is_bot": true, "positions": [], "events": [{"type": "death", "px": 529.87, "py": 783.49, "t": 286, "raw": "BotKilled"}]}, {"user_id": "inferred_bot_4", "is_bot": true, "positions": [], "events": [{"type": "death", "px": 418.59, "py": 657.3, "t": 344, "raw": "BotKilled"}]}, {"user_id": "inferred_bot_5", "is_bot": true, "positions": [], "events": [{"type": "death", "px": 414.98, "py": 642.91, "t": 350, "raw": "BotKilled"}]}, {"user_id": "inferred_bot_6", "is_bot": true, "positions": [], "events": [{"type": "death", "px": 383.66, "py": 571.86, "t": 371, "raw": "BotKilled"}]}, {"user_id": "inferred_bot_7", "is_bot": true, "positions": [], "events": [{"type": "death", "px": 396.3, "py": 506.8, "t": 396, "raw": "BotKilled"}]}, {"user_id": "inferred_bot_8", "is_bot": true, "positions": [], "events": [{"type": "death", "px": 441.34, "py": 493.66, "t": 432, "raw": "BotKilled"}]}, {"user_id": "inferred_bot_9", "is_bot": true, "positions": [], "events": [{"type": "death", "px": 447.28, "py": 494.27, "t": 436, "raw": "BotKilled"}]}, {"user_id": "inferred_bot_10", "is_bot": true, "positions": [], "events": [{"type": "death", "px": 454.25, "py": 495.88, "t": 440, "raw": "BotKilled"}]}, {"user_id": "inferred_bot_11", "is_bot": true, "positions": [], "events": [{"type": "death", "px": 469.51, "py": 503.4, "t": 447, "raw": "BotKilled"}]}]}