{"match_id": "4ae72919-17a2-4246-99f5-64e6b103d4ac", "map_id": "AmbroseValley", "date": "February_10", "duration_s": 523, "human_count": 1, "bot_count": 8, "bot_kills_inferred": 8, "bot_deaths_inferred": 0, "players": [{"user_id": "036692b4-8185-422d-823a-9e4c394ba75e", "is_bot": false, "positions": [[302.36, 901.57, 0], [322.53, 894.56, 15], [352.12, 892.28, 20], [359.43, 893.45, 25], [360.0, 888.45, 30], [358.07, 887.2, 35], [368.98, 886.19, 40], [373.5, 894.68, 45], [378.28, 890.33, 50], [381.91, 903.01, 60], [383.33, 887.91, 65], [382.39, 862.39, 70], [398.53, 834.23, 75], [404.11, 815.35, 80], [416.3, 809.49, 85], [420.44, 801.89, 90], [412.68, 805.39, 95], [400.4, 803.17, 100], [409.02, 799.71, 105], [419.16, 808.69, 110], [405.81, 808.19, 115], [404.87, 801.81, 120], [406.5, 807.57, 125], [415.24, 802.53, 130], [423.85, 797.76, 135], [426.05, 816.93, 140], [433.44, 848.22, 145], [431.09, 846.3, 150], [405.91, 825.05, 155], [394.68, 800.07, 160], [385.81, 778.42, 166], [378.52, 742.92, 171], [358.31, 712.29, 176], [332.91, 668.18, 186], [311.23, 646.42, 191], [302.27, 626.31, 196], [301.03, 600.82, 201], [302.31, 570.1, 206], [311.84, 548.95, 211], [327.48, 543.52, 216], [350.54, 531.96, 221], [361.85, 533.16, 226], [360.76, 530.26, 231], [371.03, 526.09, 236], [369.23, 537.2, 241], [358.62, 525.12, 251], [331.54, 529.92, 256], [314.82, 536.93, 261], [299.89, 533.75, 266], [300.94, 527.16, 271], [304.44, 537.39, 276], [300.67, 541.41, 281], [282.01, 541.96, 286], [271.5, 511.96, 291], [276.08, 484.88, 296], [292.16, 461.44, 301], [279.04, 482.43, 306], [279.95, 477.23, 311], [288.61, 454.54, 316], [291.86, 418.19, 321], [295.97, 417.57, 326], [316.5, 433.14, 331], [342.16, 423.53, 336], [354.84, 434.77, 342], [385.52, 427.88, 347], [417.19, 442.28, 352], [442.22, 461.51, 357], [461.13, 480.22, 362], [485.23, 484.7, 367], [512.26, 497.02, 372], [529.22, 493.21, 377], [539.33, 487.8, 387], [541.14, 486.52, 392], [569.47, 492.46, 397], [577.47, 523.44, 402], [576.76, 555.09, 407], [575.77, 561.13, 422], [573.1, 565.36, 427], [591.87, 570.6, 432], [591.19, 575.26, 447], [589.03, 564.7, 452], [571.4, 558.06, 457], [576.22, 559.17, 462], [575.58, 560.7, 472], [570.1, 560.61, 477], [577.15, 571.38, 482], [580.94, 577.18, 487], [586.98, 552.24, 492], [582.92, 543.29, 497], [576.83, 542.63, 502], [569.37, 535.48, 507], [578.2, 539.2, 512], [577.03, 550.56, 517], [583.24, 554.61, 523]], "events": [{"type": "loot", "px": 358.74, "py": 891.81, "t": 22, "raw": "Loot"}, {"type": "loot", "px": 361.14, "py": 894.31, "t": 23, "raw": "Loot"}, {"type": "loot", "px": 361.83, "py": 891.87, "t": 28, "raw": "Loot"}, {"type": "loot", "px": 358.74, "py": 888.62, "t": 30, "raw": "Loot"}, {"type": "loot", "px": 354.86, "py": 883.13, "t": 33, "raw": "Loot"}, {"type": "loot", "px": 368.98, "py": 886.19, "t": 40, "raw": "Loot"}, {"type": "loot", "px": 372.38, "py": 894.92, "t": 44, "raw": "Loot"}, {"type": "loot", "px": 374.54, "py": 894.9, "t": 46, "raw": "Loot"}, {"type": "loot", "px": 380.79, "py": 892.36, "t": 58, "raw": "Loot"}, {"type": "loot", "px": 404.11, "py": 815.35, "t": 81, "raw": "Loot"}, {"type": "loot", "px": 405.78, "py": 815.28, "t": 82, "raw": "Loot"}, {"type": "loot", "px": 420.44, "py": 801.89, "t": 90, "raw": "Loot"}, {"type": "loot", "px": 416.26, "py": 799.65, "t": 93, "raw": "Loot"}, {"type": "loot", "px": 400.4, "py": 803.17, "t": 100, "raw": "Loot"}, {"type": "loot", "px": 419.16, "py": 808.69, "t": 112, "raw": "Loot"}, {"type": "loot", "px": 404.87, "py": 801.81, "t": 120, "raw": "Loot"}, {"type": "loot", "px": 406.29, "py": 805.13, "t": 124, "raw": "Loot"}, {"type": "loot", "px": 413.56, "py": 798.72, "t": 132, "raw": "Loot"}, {"type": "loot", "px": 360.67, "py": 708.57, "t": 178, "raw": "Loot"}, {"type": "loot", "px": 306.97, "py": 527.89, "t": 270, "raw": "Loot"}, {"type": "kill", "px": 280.1, "py": 477.62, "t": 308, "raw": "BotKill"}, {"type": "loot", "px": 279.95, "py": 477.23, "t": 310, "raw": "Loot"}, {"type": "loot", "px": 279.95, "py": 477.23, "t": 311, "raw": "Loot"}, {"type": "loot", "px": 291.71, "py": 418.35, "t": 322, "raw": "Loot"}, {"type": "loot", "px": 291.71, "py": 418.35, "t": 323, "raw": "Loot"}, {"type": "loot", "px": 342.13, "py": 422.62, "t": 339, "raw": "Loot"}, {"type": "loot", "px": 531.71, "py": 493.56, "t": 381, "raw": "Loot"}, {"type": "loot", "px": 540.38, "py": 487.54, "t": 390, "raw": "Loot"}, {"type": "kill", "px": 577.24, "py": 560.52, "t": 419, "raw": "BotKill"}, {"type": "loot", "px": 563.24, "py": 562.92, "t": 425, "raw": "Loot"}, {"type": "loot", "px": 591.87, "py": 570.6, "t": 441, "raw": "Loot"}, {"type": "loot", "px": 591.87, "py": 570.6, "t": 442, "raw": "Loot"}, {"type": "kill", "px": 567.54, "py": 560.76, "t": 478, "raw": "BotKill"}, {"type": "kill", "px": 580.48, "py": 579.92, "t": 485, "raw": "BotKill"}, {"type": "loot", "px": 579.7, "py": 581.01, "t": 486, "raw": "Loot"}, {"type": "kill", "px": 587.02, "py": 552.52, "t": 492, "raw": "BotKill"}, {"type": "loot", "px": 591.19, "py": 541.14, "t": 495, "raw": "Loot"}, {"type": "kill", "px": 571.54, "py": 536.39, "t": 507, "raw": "BotKill"}, {"type": "kill", "px": 577.11, "py": 539.23, "t": 513, "raw": "BotKill"}, {"type": "kill", "px": 576.91, "py": 545.83, "t": 516, "raw": "BotKill"}], "raw_events": ["Position", "Position", "Position", "Loot", "Loot", "Position", "Loot", "Position", "Loot", "Loot", "Position", "Position", "Loot", "Loot", "Position", "Loot", "Position", "Loot", "Position", "Position", "Position", "Position", "Position", "Loot", "Loot", "Position", "Position", "Loot", "Loot", "Position", "Loot", "Position", "Position", "Position", "Loot", "Position", "Loot", "Position", "Loot", "Position", "Position", "Loot", "Position", "Position", "Position", "Position", "Position", "Position", "Position", "Position", "Position", "Loot", "Position", "Position", "Position", "Position", "Position", "Position", "Position", "Position", "Position", "Position", "Position", "Position", "Position", "Position", "Position", "Position", "Loot", "Position", "Position", "Position", "Position", "Position", "Position", "Position", "Position", "BotKill", "Loot", "Loot", "Position", "Position", "Position", "Loot", "Loot", "Position", "Position", "Position", "Loot", "Position", "Position", "Position", "Position", "Position", "Position", "Position", "Position", "Loot", "Position", "Loot", "Position", "Position", "Position", "Position", "BotKill", "Position", "Loot", "Position", "Position", "Loot", "Loot", "Position", "Position", "Position", "Position", "Position", "Position", "BotKill", "Position", "BotKill", "Loot", "Position", "BotKill", "Position", "Loot", "Position", "Position", "BotKill", "Position", "Position", "BotKill", "BotKill", "Position", "Position"]}, {"user_id": "inferred_bot_1", "is_bot": true, "positions": [], "events": [{"type": "death", "px": 280.1, "py": 477.62, "t": 308, "raw": "BotKilled"}]}, {"user_id": "inferred_bot_2", "is_bot": true, "positions": [], "events": [{"type": "death", "px": 577.24, "py": 560.52, "t": 419, "raw": "BotKilled"}]}, {"user_id": "inferred_bot_3", "is_bot": true, "positions": [], "events": [{"type": "death", "px": 567.54, "py": 560.76, "t": 478, "raw": "BotKilled"}]}, {"user_id": "inferred_bot_4", "is_bot": true, "positions": [], "events": [{"type": "death", "px": 580.48, "py": 579.92, "t": 485, "raw": "BotKilled"}]}, {"user_id": "inferred_bot_5", "is_bot": true, "positions": [], "events": [{"type": "death", "px": 587.02, "py": 552.52, "t": 492, "raw": "BotKilled"}]}, {"user_id": "inferred_bot_6", "is_bot": true, "positions": [], "events": [{"type": "death", "px": 571.54, "py": 536.39, "t": 507, "raw": "BotKilled"}]}, {"user_id": "inferred_bot_7", "is_bot": true, "positions": [], "events": [{"type": "death", "px": 577.11, "py": 539.23, "t": 513, "raw": "BotKilled"}]}, {"user_id": "inferred_bot_8", "is_bot": true, "positions": [], "events": [{"type": "death", "px": 576.91, "py": 545.83, "t": 516, "raw": "BotKilled"}]}]}