{"match_id": "cc30d720-d0b9-499b-b471-27be602dd2d8", "map_id": "AmbroseValley", "date": "February_10", "duration_s": 760, "human_count": 1, "bot_count": 9, "bot_kills_inferred": 9, "bot_deaths_inferred": 1, "players": [{"user_id": "24bd210d-3b53-4f06-acf1-a0e0385641b6", "is_bot": false, "positions": [[302.4, 902.07, 0], [308.66, 895.99, 21], [321.17, 890.06, 26], [340.13, 888.76, 31], [355.27, 893.03, 36], [361.37, 891.91, 41], [365.06, 888.02, 46], [374.49, 894.91, 51], [378.92, 891.84, 61], [388.39, 869.68, 66], [405.12, 842.65, 71], [401.56, 824.46, 76], [404.02, 815.35, 81], [410.71, 819.11, 86], [422.52, 819.71, 91], [419.12, 809.87, 101], [414.43, 810.79, 111], [410.48, 811.12, 116], [421.25, 809.83, 121], [418.05, 810.91, 131], [402.89, 806.97, 136], [406.29, 805.1, 146], [412.44, 802.27, 151], [416.18, 803.96, 156], [414.48, 791.66, 166], [423.41, 762.31, 171], [430.75, 741.71, 176], [430.23, 742.12, 181], [433.34, 732.67, 186], [422.29, 704.94, 191], [402.04, 678.96, 197], [404.52, 645.95, 202], [408.1, 624.37, 207], [410.26, 627.0, 212], [409.06, 628.9, 217], [407.81, 623.99, 222], [391.34, 601.31, 227], [386.31, 597.18, 232], [388.85, 598.06, 242], [387.95, 593.65, 252], [384.86, 592.09, 257], [374.32, 593.43, 267], [364.73, 591.55, 282], [373.34, 592.21, 287], [383.56, 587.38, 292], [368.18, 578.17, 297], [360.86, 584.15, 302], [355.7, 588.49, 307], [331.41, 597.32, 312], [298.48, 590.9, 317], [262.27, 588.47, 322], [238.33, 594.07, 327], [235.53, 582.67, 332], [224.81, 574.18, 337], [244.34, 552.46, 347], [274.23, 542.47, 352], [285.14, 528.35, 357], [284.2, 534.01, 362], [285.36, 530.73, 367], [294.94, 534.0, 372], [306.3, 533.96, 378], [302.86, 540.08, 398], [306.63, 533.87, 403], [307.99, 535.99, 408], [295.08, 538.13, 413], [300.22, 547.96, 423], [316.9, 528.21, 428], [320.43, 513.7, 433], [327.84, 510.01, 443], [334.46, 540.24, 448], [339.34, 552.87, 453], [350.29, 562.57, 468], [333.18, 556.62, 473], [333.81, 561.52, 498], [332.46, 557.27, 503], [331.82, 560.25, 538], [342.62, 561.3, 543], [333.32, 556.85, 548], [333.03, 563.72, 554], [332.35, 566.83, 559], [354.76, 569.74, 564], [372.64, 561.18, 569], [391.04, 549.51, 574], [389.04, 532.65, 579], [390.01, 525.5, 584], [392.47, 514.36, 594], [394.46, 505.51, 599], [399.39, 493.62, 604], [401.85, 483.16, 609], [414.41, 485.12, 614], [418.8, 486.86, 619], [434.23, 489.72, 624], [445.92, 491.81, 629], [452.96, 486.72, 634], [454.55, 496.83, 649], [466.77, 506.0, 654], [474.06, 514.0, 659], [476.64, 519.81, 664], [485.26, 523.12, 669], [511.55, 510.31, 674], [546.96, 509.21, 679], [573.83, 532.83, 684], [586.0, 552.49, 689], [581.96, 546.17, 694], [595.99, 556.29, 699], [598.39, 561.1, 719], [575.49, 573.66, 724], [564.36, 608.13, 730], [536.69, 623.87, 735], [515.38, 623.42, 740], [483.92, 636.5, 745], [448.53, 646.76, 750], [415.32, 649.6, 755], [418.08, 656.23, 760]], "events": [{"type": "loot", "px": 360.94, "py": 894.12, "t": 37, "raw": "Loot"}, {"type": "loot", "px": 361.37, "py": 891.91, "t": 42, "raw": "Loot"}, {"type": "loot", "px": 361.37, "py": 891.91, "t": 42, "raw": "Loot"}, {"type": "loot", "px": 373.54, "py": 894.9, "t": 48, "raw": "Loot"}, {"type": "loot", "px": 373.54, "py": 894.9, "t": 48, "raw": "Loot"}, {"type": "loot", "px": 374.49, "py": 894.91, "t": 50, "raw": "Loot"}, {"type": "loot", "px": 371.27, "py": 888.49, "t": 55, "raw": "Loot"}, {"type": "loot", "px": 371.27, "py": 888.49, "t": 55, "raw": "Loot"}, {"type": "loot", "px": 401.56, "py": 824.46, "t": 78, "raw": "Loot"}, {"type": "loot", "px": 404.02, "py": 815.35, "t": 82, "raw": "Loot"}, {"type": "loot", "px": 420.26, "py": 801.0, "t": 103, "raw": "Loot"}, {"type": "loot", "px": 420.26, "py": 801.0, "t": 103, "raw": "Loot"}, {"type": "loot", "px": 414.96, "py": 811.2, "t": 110, "raw": "Loot"}, {"type": "loot", "px": 401.24, "py": 806.0, "t": 140, "raw": "Loot"}, {"type": "loot", "px": 406.29, "py": 805.18, "t": 146, "raw": "Loot"}, {"type": "loot", "px": 416.18, "py": 803.96, "t": 156, "raw": "Loot"}, {"type": "loot", "px": 412.8, "py": 799.54, "t": 158, "raw": "Loot"}, {"type": "kill", "px": 410.26, "py": 627.0, "t": 215, "raw": "BotKill"}, {"type": "kill", "px": 388.85, "py": 598.06, "t": 242, "raw": "BotKill"}, {"type": "kill", "px": 388.16, "py": 595.38, "t": 248, "raw": "BotKill"}, {"type": "kill", "px": 387.95, "py": 593.65, "t": 251, "raw": "BotKill"}, {"type": "loot", "px": 385.5, "py": 592.7, "t": 255, "raw": "Loot"}, {"type": "loot", "px": 385.5, "py": 592.7, "t": 255, "raw": "Loot"}, {"type": "loot", "px": 385.5, "py": 592.7, "t": 255, "raw": "Loot"}, {"type": "loot", "px": 385.5, "py": 592.7, "t": 255, "raw": "Loot"}, {"type": "kill", "px": 373.69, "py": 593.58, "t": 272, "raw": "BotKill"}, {"type": "loot", "px": 374.65, "py": 591.25, "t": 276, "raw": "Loot"}, {"type": "loot", "px": 374.65, "py": 591.25, "t": 276, "raw": "Loot"}, {"type": "loot", "px": 384.12, "py": 591.85, "t": 290, "raw": "Loot"}, {"type": "loot", "px": 384.12, "py": 591.85, "t": 290, "raw": "Loot"}, {"type": "loot", "px": 383.56, "py": 587.38, "t": 292, "raw": "Loot"}, {"type": "loot", "px": 383.56, "py": 587.38, "t": 292, "raw": "Loot"}, {"type": "kill", "px": 224.81, "py": 574.18, "t": 337, "raw": "BotKill"}, {"type": "loot", "px": 224.81, "py": 574.18, "t": 338, "raw": "Loot"}, {"type": "loot", "px": 224.81, "py": 574.18, "t": 338, "raw": "Loot"}, {"type": "kill", "px": 285.14, "py": 528.35, "t": 357, "raw": "BotKill"}, {"type": "loot", "px": 282.15, "py": 537.64, "t": 365, "raw": "Loot"}, {"type": "loot", "px": 295.22, "py": 534.45, "t": 370, "raw": "Loot"}, {"type": "loot", "px": 295.22, "py": 534.45, "t": 370, "raw": "Loot"}, {"type": "loot", "px": 306.3, "py": 533.96, "t": 375, "raw": "Loot"}, {"type": "loot", "px": 307.03, "py": 534.21, "t": 404, "raw": "Loot"}, {"type": "loot", "px": 295.08, "py": 538.13, "t": 413, "raw": "Loot"}, {"type": "kill", "px": 320.43, "py": 513.7, "t": 433, "raw": "BotKill"}, {"type": "loot", "px": 320.12, "py": 513.61, "t": 437, "raw": "Loot"}, {"type": "loot", "px": 351.33, "py": 555.55, "t": 466, "raw": "Loot"}, {"type": "loot", "px": 335.21, "py": 556.22, "t": 481, "raw": "Loot"}, {"type": "loot", "px": 331.98, "py": 561.14, "t": 496, "raw": "Loot"}, {"type": "loot", "px": 332.82, "py": 557.13, "t": 518, "raw": "Loot"}, {"type": "loot", "px": 332.82, "py": 557.13, "t": 528, "raw": "Loot"}, {"type": "loot", "px": 333.32, "py": 556.85, "t": 548, "raw": "Loot"}, {"type": "loot", "px": 389.04, "py": 532.65, "t": 579, "raw": "Loot"}, {"type": "kill", "px": 394.46, "py": 505.51, "t": 601, "raw": "BotKill"}, {"type": "loot", "px": 401.85, "py": 483.16, "t": 607, "raw": "Loot"}, {"type": "loot", "px": 401.85, "py": 483.16, "t": 607, "raw": "Loot"}, {"type": "loot", "px": 452.96, "py": 486.72, "t": 641, "raw": "Loot"}, {"type": "loot", "px": 452.96, "py": 486.72, "t": 643, "raw": "Loot"}, {"type": "loot", "px": 595.99, "py": 556.29, "t": 705, "raw": "Loot"}, {"type": "loot", "px": 595.99, "py": 556.29, "t": 708, "raw": "Loot"}, {"type": "loot", "px": 595.99, "py": 556.29, "t": 715, "raw": "Loot"}, {"type": "loot", "px": 597.3, "py": 559.81, "t": 718, "raw": "Loot"}, {"type": "death", "px": 418.37, "py": 656.0, "t": 758, "raw": "BotKilled"}], "raw_events": ["Position", "Position", "Position", "Position", "Position", "Loot", "Position", "Loot", "Loot", "Position", "Loot", "Loot", "Loot", "Position", "Loot", "Loot", "Position", "Position", "Position", "Position", "Loot", "Position", "Loot", "Position", "Position", "Position", "Loot", "Loot", "Loot", "Position", "Position", "Position", "Position", "Position", "Loot", "Loot", "Position", "Position", "Loot", "Position", "Loot", "Position", "Position", "Position", "Position", "Position", "Position", "Position", "Position", "Position", "Position", "BotKill", "Position", "Position", "Position", "Position", "Position", "BotKill", "BotKill", "BotKill", "Position", "Loot", "Loot", "Loot", "Loot", "Position", "Position", "BotKill", "Loot", "Loot", "Position", "Position", "Loot", "Loot", "Loot", "Loot", "Position", "Position", "Position", "Position", "Position", "Position", "Position", "Position", "Position", "BotKill", "Position", "Loot", "Loot", "Position", "Position", "BotKill", "Position", "Position", "Loot", "Position", "Loot", "Loot", "Position", "Loot", "Position", "Position", "Position", "Loot", "Position", "Loot", "Position", "Position", "Position", "Position", "BotKill", "Loot", "Position", "Position", "Position", "Loot", "Position", "Position", "Loot", "Loot", "Position", "Position", "Loot", "Loot", "Position", "Position", "Loot", "Position", "Position", "Position", "Position", "Position", "Position", "Position", "Loot", "Position", "Position", "Position", "BotKill", "Position", "Loot", "Loot", "Position", "Position", "Position", "Position", "Position", "Position", "Loot", "Loot", "Position", "Position", "Position", "Position", "Position", "Position", "Position", "Position", "Position", "Position", "Position", "Loot", "Loot", "Loot", "Loot", "Position", "Position", "Position", "Position", "Position", "Position", "Position", "Position", "BotKilled", "Position"]}, {"user_id": "inferred_bot_1", "is_bot": true, "positions": [], "events": [{"type": "death", "px": 410.26, "py": 627.0, "t": 215, "raw": "BotKilled"}]}, {"user_id": "inferred_bot_2", "is_bot": true, "positions": [], "events": [{"type": "death", "px": 388.85, "py": 598.06, "t": 242, "raw": "BotKilled"}]}, {"user_id": "inferred_bot_3", "is_bot": true, "positions": [], "events": [{"type": "death", "px": 388.16, "py": 595.38, "t": 248, "raw": "BotKilled"}]}, {"user_id": "inferred_bot_4", "is_bot": true, "positions": [], "events": [{"type": "death", "px": 387.95, "py": 593.65, "t": 251, "raw": "BotKilled"}]}, {"user_id": "inferred_bot_5", "is_bot": true, "positions": [], "events": [{"type": "death", "px": 373.69, "py": 593.58, "t": 272, "raw": "BotKilled"}]}, {"user_id": "inferred_bot_6", "is_bot": true, "positions": [], "events": [{"type": "death", "px": 224.81, "py": 574.18, "t": 337, "raw": "BotKilled"}]}, {"user_id": "inferred_bot_7", "is_bot": true, "positions": [], "events": [{"type": "death", "px": 285.14, "py": 528.35, "t": 357, "raw": "BotKilled"}]}, {"user_id": "inferred_bot_8", "is_bot": true, "positions": [], "events": [{"type": "death", "px": 320.43, "py": 513.7, "t": 433, "raw": "BotKilled"}]}, {"user_id": "inferred_bot_9", "is_bot": true, "positions": [], "events": [{"type": "death", "px": 394.46, "py": 505.51, "t": 601, "raw": "BotKilled"}]}]}